locksys/__init__.py
locksys/locksys.py
locksys-0.1.0.dist-info/LICENSE
locksys-0.1.0.dist-info/METADATA
locksys-0.1.0.dist-info/WHEEL
locksys-0.1.0.dist-info/top_level.txt
locksys-0.1.0.dist-info/RECORD
