Metadata-Version: 2.1
Name: locksys
Version: 0.1.0
Summary: A Python library for securely retrieving API keys from 1Password
Home-page: https://github.com/yourusername/locksys
Author: Mark Powers
Author-email: mpoweru@lifsys.com
Classifier: Development Status :: 3 - Alpha
Classifier: Intended Audience :: Developers
Classifier: License :: OSI Approved :: MIT License
Classifier: Operating System :: OS Independent
Classifier: Programming Language :: Python :: 3
Classifier: Programming Language :: Python :: 3.6
Classifier: Programming Language :: Python :: 3.7
Classifier: Programming Language :: Python :: 3.8
Classifier: Programming Language :: Python :: 3.9
Requires-Python: >=3.6
License-File: LICENSE
Requires-Dist: onepasswordconnectsdk
